solution_efe_client_leader/__init__.py
solution_efe_client_leader/leaderService.py
solution_efe_client_leader-1.0.0.dist-info/METADATA
solution_efe_client_leader-1.0.0.dist-info/WHEEL
solution_efe_client_leader-1.0.0.dist-info/top_level.txt
solution_efe_client_leader-1.0.0.dist-info/RECORD
